lahja/__init__.py
lahja/_snappy.py
lahja/base.py
lahja/common.py
lahja/constants.py
lahja/exceptions.py
lahja/py.typed
lahja/typing.py
lahja/asyncio/__init__.py
lahja/asyncio/endpoint.py
lahja/tools/__init__.py
lahja/tools/engine.py
lahja/tools/runner.py
lahja/tools/benchmark/__init__.py
lahja/tools/benchmark/backends.py
lahja/tools/benchmark/constants.py
lahja/tools/benchmark/logging.py
lahja/tools/benchmark/process.py
lahja/tools/benchmark/stats.py
lahja/tools/benchmark/typing.py
lahja/tools/benchmark/utils/__init__.py
lahja/tools/benchmark/utils/config.py
lahja/tools/benchmark/utils/reporting.py
lahja/tools/drivers/__init__.py
lahja/tools/drivers/actions.py
lahja/tools/drivers/driver.py
lahja/tools/drivers/initializers.py
lahja/trio/__init__.py
lahja/trio/endpoint.py
lahja/trio/future.py
lahja-0.17.0.dist-info/LICENSE
lahja-0.17.0.dist-info/METADATA
lahja-0.17.0.dist-info/WHEEL
lahja-0.17.0.dist-info/top_level.txt
lahja-0.17.0.dist-info/RECORD
