Metadata-Version: 2.1
Name: lahja
Version: 0.17.0
Summary: Generic event bus for asynchronous cross-process communication
Home-page: https://github.com/ethereum/lahja
Author: The Ethereum Foundation
Author-email: snakecharmers@ethereum.org
License: MIT
Keywords: eventbus asyncio trio
Platform: UNKNOWN
Classifier: Development Status :: 3 - Alpha
Classifier: Intended Audience :: Developers
Classifier: License :: OSI Approved :: MIT License
Classifier: Natural Language :: English
Classifier: Programming Language :: Python :: 3
Classifier: Programming Language :: Python :: 3.6
Classifier: Programming Language :: Python :: 3.7
Classifier: Programming Language :: Python :: Implementation :: PyPy
Requires-Python: >=3.6, <4
Requires-Dist: async-generator (<2,>=1.10)
Requires-Dist: trio (<0.17,>=0.16)
Requires-Dist: trio-typing (<0.6.0,>=0.5.0)
Provides-Extra: dev
Requires-Dist: bumpversion (<1,>=0.5.3) ; extra == 'dev'
Requires-Dist: pytest-watch (<5,>=4.1.0) ; extra == 'dev'
Requires-Dist: wheel ; extra == 'dev'
Requires-Dist: twine ; extra == 'dev'
Requires-Dist: ipython ; extra == 'dev'
Requires-Dist: cytoolz (<1.0.0,>=0.9.0) ; extra == 'dev'
Requires-Dist: pytest (<6,>=5.1.3) ; extra == 'dev'
Requires-Dist: pytest-timeout (==1.3.3) ; extra == 'dev'
Requires-Dist: pytest-xdist (==1.25.0) ; extra == 'dev'
Requires-Dist: tox (<3,>=2.9.1) ; extra == 'dev'
Requires-Dist: black (==19.3b) ; extra == 'dev'
Requires-Dist: flake8 (==3.7.7) ; extra == 'dev'
Requires-Dist: isort (==4.3.18) ; extra == 'dev'
Requires-Dist: mypy (==0.740) ; extra == 'dev'
Requires-Dist: pydocstyle (<4,>=3.0.0) ; extra == 'dev'
Requires-Dist: Sphinx (<2,>=1.6.5) ; extra == 'dev'
Requires-Dist: sphinx-rtd-theme (>=0.1.9) ; extra == 'dev'
Requires-Dist: towncrier (<20,>=19.2.0) ; extra == 'dev'
Provides-Extra: doc
Requires-Dist: Sphinx (<2,>=1.6.5) ; extra == 'doc'
Requires-Dist: sphinx-rtd-theme (>=0.1.9) ; extra == 'doc'
Requires-Dist: towncrier (<20,>=19.2.0) ; extra == 'doc'
Provides-Extra: lint
Requires-Dist: black (==19.3b) ; extra == 'lint'
Requires-Dist: flake8 (==3.7.7) ; extra == 'lint'
Requires-Dist: isort (==4.3.18) ; extra == 'lint'
Requires-Dist: mypy (==0.740) ; extra == 'lint'
Requires-Dist: pydocstyle (<4,>=3.0.0) ; extra == 'lint'
Provides-Extra: snappy
Requires-Dist: python-snappy (<1,>=0.5.3) ; extra == 'snappy'
Provides-Extra: test
Requires-Dist: cytoolz (<1.0.0,>=0.9.0) ; extra == 'test'
Requires-Dist: pytest (<6,>=5.1.3) ; extra == 'test'
Requires-Dist: pytest-timeout (==1.3.3) ; extra == 'test'
Requires-Dist: pytest-xdist (==1.25.0) ; extra == 'test'
Requires-Dist: tox (<3,>=2.9.1) ; extra == 'test'
Provides-Extra: test-asyncio
Requires-Dist: pytest-asyncio (<0.11,>=0.10.0) ; extra == 'test-asyncio'
Provides-Extra: test-trio
Requires-Dist: pytest-trio (==0.6.0) ; extra == 'test-trio'
